metar/Datatypes.py
metar/Datatypes.pyi
metar/Metar.py
metar/Metar.pyi
metar/Station.py
metar/Station.pyi
metar/__init__.py
metar/nsd_cccc.txt
metar/py.typed
metar-1.11.0.dist-info/LICENSE
metar-1.11.0.dist-info/METADATA
metar-1.11.0.dist-info/WHEEL
metar-1.11.0.dist-info/top_level.txt
metar-1.11.0.dist-info/RECORD
