Metadata-Version: 2.1
Name: metar
Version: 1.11.0
Summary: Metar - a package to parse METAR-coded weather reports
Home-page: https://github.com/python-metar/python-metar
Author: Tom Pollard
Author-email: pollard@alum.mit.edu
License: BSD
Platform: Python 2.5 and later.
Classifier: Development Status :: 5 - Production/Stable
Classifier: License :: OSI Approved :: BSD License
Classifier: Operating System :: OS Independent
Classifier: Programming Language :: Python
Classifier: Intended Audience :: Science/Research
Classifier: Topic :: Software Development :: Libraries :: Python Modules
Provides-Extra: test
License-File: LICENSE
